parlant/contrib/activefence/__init__.py
parlant/contrib/activefence/activefence.py
parlant/contrib/activefence/moderation_service.py
parlant_activefence-0.1.2.dist-info/licenses/LICENSE
parlant_activefence-0.1.2.dist-info/METADATA
parlant_activefence-0.1.2.dist-info/WHEEL
parlant_activefence-0.1.2.dist-info/top_level.txt
parlant_activefence-0.1.2.dist-info/RECORD
