Metadata-Version: 2.4
Name: parlant-activefence
Version: 0.1.2
Summary: ActiveFence integration for Parlant
Project-URL: Repository, https://github.com/ActiveFence/parlant-activefence
Keywords: parlant,activefence,security,threat-detection,content-moderation
Classifier: Operating System :: OS Independent
Classifier: Programming Language :: Python :: 3
Requires-Python: >=3.9
License-File: LICENSE
Requires-Dist: parlant>=3.0.2
Requires-Dist: activefence-client-sdk>=0.0.11
Provides-Extra: dev
Requires-Dist: pytest>=6.0; extra == "dev"
Requires-Dist: pytest-cov>=2.0; extra == "dev"
Requires-Dist: black>=21.0; extra == "dev"
Requires-Dist: flake8>=3.8; extra == "dev"
Requires-Dist: mypy>=0.800; extra == "dev"
Dynamic: license-file
